financepype/__init__.py
financepype/assets/__init__.py
financepype/assets/asset.py
financepype/assets/asset_id.py
financepype/assets/blockchain.py
financepype/assets/centralized_asset.py
financepype/assets/contract.py
financepype/assets/factory.py
financepype/assets/spot.py
financepype/constants.py
financepype/markets/__init__.py
financepype/markets/candle.py
financepype/markets/funding.py
financepype/markets/market.py
financepype/markets/orderbook/__init__.py
financepype/markets/orderbook/exceptions.py
financepype/markets/orderbook/models.py
financepype/markets/orderbook/tracker.py
financepype/markets/position.py
financepype/markets/trade.py
financepype/markets/trading_pair.py
financepype/operations/__init__.py
financepype/operations/fees.py
financepype/operations/operation.py
financepype/operations/orders/__init__.py
financepype/operations/orders/events.py
financepype/operations/orders/models.py
financepype/operations/orders/order.py
financepype/operations/orders/proposal.py
financepype/operations/orders/tracker.py
financepype/operations/proposal.py
financepype/operations/tracker.py
financepype/operations/transactions/__init__.py
financepype/operations/transactions/events.py
financepype/operations/transactions/models.py
financepype/operations/transactions/proposal.py
financepype/operations/transactions/tracker.py
financepype/operations/transactions/transaction.py
financepype/operators/__init__.py
financepype/operators/blockchains/__init__.py
financepype/operators/blockchains/blockchain.py
financepype/operators/blockchains/identifier.py
financepype/operators/blockchains/models.py
financepype/operators/dapps/__init__.py
financepype/operators/dapps/dapp.py
financepype/operators/exchanges/__init__.py
financepype/operators/exchanges/exchange.py
financepype/operators/exchanges/orderbook_exchange.py
financepype/operators/factory.py
financepype/operators/nonce_creator.py
financepype/operators/operator.py
financepype/owners/__init__.py
financepype/owners/account.py
financepype-0.1.10.dist-info/LICENSE
financepype-0.1.10.dist-info/METADATA
financepype-0.1.10.dist-info/WHEEL
financepype-0.1.10.dist-info/RECORD
