Metadata-Version: 2.3
Name: financepype
Version: 0.1.10
Summary: FinancePype is a Python library for trading on centralized and decentralized exchanges.
Author: Gianluca Pagliara
Author-email: pagliara.gianluca@gmail.com
Requires-Python: >=3.13,<4.0
Classifier: Programming Language :: Python :: 3
Classifier: Programming Language :: Python :: 3.13
Requires-Dist: bidict (>=0.23.1,<0.24.0)
Requires-Dist: boto3 (>=1.35.90,<2.0.0)
Requires-Dist: cachetools (>=4.2.2,<5.0.0)
Requires-Dist: chronopype (>=0.2.1,<0.3.0)
Requires-Dist: eventspype (>=1.0.0,<2.0.0)
Requires-Dist: pandas (>=2.2.1,<3.0.0)
Requires-Dist: pydantic (>=2.10.4,<3.0.0)
Requires-Dist: sortedcontainers (>=2.4.0,<3.0.0)
Requires-Dist: streamlit (>=1.32.0,<2.0.0)
Requires-Dist: types-cachetools (>=4.2.10,<5.0.0)
